hbspark/__init__.py
hbspark/_hb_session.py
hbspark/_utils.py
hbspark/table.py
hbspark-0.0.4.dist-info/LICENSE
hbspark-0.0.4.dist-info/METADATA
hbspark-0.0.4.dist-info/WHEEL
hbspark-0.0.4.dist-info/top_level.txt
hbspark-0.0.4.dist-info/RECORD
