Metadata-Version: 2.1
Name: hbspark
Version: 0.0.4
Summary: Package to pipe data from HBase to Spark (2+)
Home-page: https://github.com/kxz167/hbspark
Author: Kris Zhao
License: UNKNOWN
Project-URL: Bug Tracker, https://github.com/kxz167/hbspark/issues
Platform: UNKNOWN
Classifier: Programming Language :: Python :: 3
Classifier: License :: OSI Approved :: GNU General Public License v3 (GPLv3)
Classifier: Operating System :: OS Independent
Requires-Python: >=2
License-File: LICENSE
